pymsgboxexample20250510zAx.py
pymsgboxexample20250510zax-0.1.2.dist-info/METADATA
pymsgboxexample20250510zax-0.1.2.dist-info/WHEEL
pymsgboxexample20250510zax-0.1.2.dist-info/RECORD
