Metadata-Version: 2.3
Name: pymsgboxexample20250510zAx
Version: 0.1.2
Summary: Hello world example
Author: Your Name
Author-email: you@example.com
Requires-Python: >=3.6
Classifier: Programming Language :: Python :: 3
Classifier: Programming Language :: Python :: 3.6
Classifier: Programming Language :: Python :: 3.7
Classifier: Programming Language :: Python :: 3.8
Classifier: Programming Language :: Python :: 3.9
Classifier: Programming Language :: Python :: 3.10
Classifier: Programming Language :: Python :: 3.11
Classifier: Programming Language :: Python :: 3.12
Classifier: Programming Language :: Python :: 3.13
Requires-Dist: pymsgbox (>=1.0.9,<2.0.0)
